LICENSE
MANIFEST.in
README.md
pyproject.toml
requirements.txt
setup.cfg
setup.py
tox.ini
bnbxrate/__init__.py
bnbxrate/bnb.py
bnbxrate.egg-info/PKG-INFO
bnbxrate.egg-info/SOURCES.txt
bnbxrate.egg-info/dependency_links.txt
bnbxrate.egg-info/entry_points.txt
bnbxrate.egg-info/top_level.txt
bnbxrate/__pycache__/__init__.cpython-38.pyc
bnbxrate/__pycache__/bnb.cpython-38.pyc
tests/__init__.py
tests/basic_test.py
tests/__pycache__/__init__.cpython-38.pyc
tests/__pycache__/basic_test.cpython-38-pytest-5.4.3.pyc
tests/__pycache__/basic_test.cpython-38.pyc