Metadata-Version: 2.1
Name: bnbxrate
Version: 0.1.0
Summary: Bulgarian National Bank - get history exchage rates
Home-page: https://github.com/hristo-mavrodiev/bnbxrate
Author: Hristo Mavrodiev
Author-email: h.mavrodiev@abv.bg
License: UNKNOWN
Platform: UNKNOWN
